giftsnippet/__init__.py
giftsnippet/console.py
giftsnippet/gift.py
giftsnippet/highlight.py
giftsnippet/image.py
giftsnippet-0.2.4.dist-info/METADATA
giftsnippet-0.2.4.dist-info/WHEEL
giftsnippet-0.2.4.dist-info/entry_points.txt
giftsnippet-0.2.4.dist-info/top_level.txt
giftsnippet-0.2.4.dist-info/RECORD
