Metadata-Version: 2.1
Name: giftsnippet
Version: 0.2.4
Summary: Integrate highlighted source code images with data uris into your gift questions
Home-page: http://github.com/stefanhuber/giftsnippet
Author: Stefan Huber
Author-email: mail@stefanhuber.at
License: BSD
Keywords: gift moodle code-formatting
Platform: UNKNOWN
Requires-Dist: wheel
Requires-Dist: Pygments
Requires-Dist: Pillow
